{
	"editor": {
		"backDropShape": "entity/humanoid/seraph-hairless",
		"allAngles": true,
		"entityTextureMode": true
	},
	"textureWidth": 48,
	"textureHeight": 48,
	"textureSizes": {
		"hair": [48,48]
	},
	"textures": {
		"hair": "entity/humanoid/seraphskinparts/hair/lightgray"
	},
	"elements": [
		{
			"name": "Hair-Base",
			"stepParentName": "Head",
			"from": [ -0.3, -3.2, -0.3 ],
			"to": [ 5.7, 5.3, 5.2 ],
			"renderPass": 1,
			"autoUnwrap": false,
			"uv": [ 0.0, 0.0 ],
			"rotationOrigin": [ 2.5, 3.0, 2.5 ],
			"faces": {
				"north": { "texture": "#hair", "uv": [ 7.0, 36.0, 13.0, 44.5 ], "windMode": [-1,-1,-1,-1], "windData": [1,1,1,1], "enabled": false },
				"east": { "texture": "#hair", "uv": [ 0.5, 37.0, 6.0, 45.5 ], "windMode": [-1,-1,-1,-1], "windData": [1,1,1,1], "enabled": false },
				"south": { "texture": "#hair", "uv": [ 17.0, 36.0, 23.0, 44.5 ], "windMode": [-1,-1,-1,-1], "windData": [1,1,1,1], "enabled": false },
				"west": { "texture": "#hair", "uv": [ 12.0, 36.0, 17.5, 44.5 ], "windMode": [-1,-1,-1,-1], "windData": [1,1,1,1], "enabled": false },
				"up": { "texture": "#hair", "uv": [ 24.0, 0.0, 29.5, 6.0 ], "rotation": 90, "enabled": false },
				"down": { "texture": "#null", "uv": [ 6.0, 0.0, 12.0, 5.5 ], "enabled": false }
			},
			"children": [
				{
					"name": "hair-uncovered",
					"from": [ 2.7, 6.0, 2.9 ],
					"to": [ 2.7, 6.0, 2.9 ],
					"uv": [ 0.0, 0.0 ],
					"rotationOrigin": [ 2.7, 6.0, 2.9 ],
					"rotationZ": 0.0,
					"faces": {
						"north": { "texture": "#null", "uv": [ 0.0, 0.5, 0.5, 1.0 ], "enabled": false },
						"east": { "texture": "#null", "uv": [ 0.5, 0.5, 1.0, 1.0 ], "enabled": false },
						"south": { "texture": "#null", "uv": [ 1.0, 0.5, 1.5, 1.0 ], "enabled": false },
						"west": { "texture": "#null", "uv": [ 1.5, 0.5, 2.0, 1.0 ], "enabled": false },
						"up": { "texture": "#null", "uv": [ 0.0, 0.0, 0.5, 0.5 ], "enabled": false },
						"down": { "texture": "#null", "uv": [ 0.5, 0.0, 1.0, 0.5 ], "enabled": false }
					},
					"children": [
						{
							"name": "dread1",
							"from": [ -1.5, 2.1, -0.5 ],
							"to": [ -0.5, 5.1, 0.5 ],
							"renderPass": 1,
							"autoUnwrap": false,
							"uv": [ 29.0, 44.0 ],
							"rotationOrigin": [ -1.0, 2.1, 0.0 ],
							"rotationX": 10.0,
							"rotationZ": 45.0,
							"faces": {
								"north": { "texture": "#hair", "uv": [ 29.0, 40.5, 30.0, 43.5 ], "rotation": 180 },
								"east": { "texture": "#hair", "uv": [ 30.0, 40.5, 31.0, 43.5 ], "rotation": 180 },
								"south": { "texture": "#hair", "uv": [ 31.0, 40.5, 32.0, 43.5 ], "rotation": 180 },
								"west": { "texture": "#hair", "uv": [ 32.0, 40.5, 33.0, 43.5 ], "rotation": 180 },
								"up": { "texture": "#null", "uv": [ 0.0, 0.0, 1.0, 1.0 ], "enabled": false },
								"down": { "texture": "#null", "uv": [ 1.0, 0.0, 2.0, 1.0 ], "enabled": false }
							}
						},
						{
							"name": "dread2",
							"from": [ -0.5, 2.1, -1.5 ],
							"to": [ 0.5, 5.1, -0.5 ],
							"renderPass": 1,
							"autoUnwrap": false,
							"uv": [ 29.0, 44.0 ],
							"rotationOrigin": [ 0.0, 2.1, -1.0 ],
							"rotationX": -22.5,
							"rotationZ": 22.5,
							"faces": {
								"north": { "texture": "#hair", "uv": [ 29.0, 40.5, 30.0, 43.5 ], "rotation": 180 },
								"east": { "texture": "#hair", "uv": [ 30.0, 40.5, 31.0, 43.5 ], "rotation": 180 },
								"south": { "texture": "#hair", "uv": [ 31.0, 40.5, 32.0, 43.5 ], "rotation": 180 },
								"west": { "texture": "#hair", "uv": [ 32.0, 40.5, 33.0, 43.5 ], "rotation": 180 },
								"up": { "texture": "#null", "uv": [ 0.0, 0.0, 1.0, 1.0 ], "enabled": false },
								"down": { "texture": "#null", "uv": [ 1.0, 0.0, 2.0, 1.0 ], "enabled": false }
							}
						},
						{
							"name": "dread3",
							"from": [ -0.5, 2.1, 0.0 ],
							"to": [ 0.5, 5.1, 1.0 ],
							"renderPass": 1,
							"autoUnwrap": false,
							"uv": [ 29.0, 44.0 ],
							"rotationOrigin": [ 0.0, 2.1, 0.5 ],
							"rotationX": 30.0,
							"rotationZ": 30.0,
							"faces": {
								"north": { "texture": "#hair", "uv": [ 29.0, 40.5, 30.0, 43.5 ], "rotation": 180 },
								"east": { "texture": "#hair", "uv": [ 30.0, 40.5, 31.0, 43.5 ], "rotation": 180 },
								"south": { "texture": "#hair", "uv": [ 31.0, 40.5, 32.0, 43.5 ], "rotation": 180 },
								"west": { "texture": "#hair", "uv": [ 32.0, 40.5, 33.0, 43.5 ], "rotation": 180 },
								"up": { "texture": "#null", "uv": [ 0.0, 0.0, 1.0, 1.0 ], "enabled": false },
								"down": { "texture": "#null", "uv": [ 1.0, 0.0, 2.0, 1.0 ], "enabled": false }
							}
						},
						{
							"name": "dread4",
							"from": [ -4.0, 2.1, -1.5 ],
							"to": [ -1.0, 3.1, -0.5 ],
							"renderPass": 1,
							"autoUnwrap": false,
							"uv": [ 30.5, 29.0 ],
							"rotationOrigin": [ -1.0, 2.6, -1.0 ],
							"rotationY": -5.0,
							"rotationZ": -10.0,
							"faces": {
								"north": { "texture": "#hair", "uv": [ 28.0, 40.5, 29.0, 43.5 ], "rotation": 270 },
								"east": { "texture": "#hair", "uv": [ 31.5, 34.0, 32.5, 35.0 ], "windMode": [-1,-1,-1,-1], "windData": [1,1,1,1] },
								"south": { "texture": "#hair", "uv": [ 28.0, 40.5, 29.0, 43.5 ], "rotation": 90 },
								"west": { "texture": "#null", "uv": [ 7.0, 1.0, 8.0, 2.0 ], "enabled": false },
								"up": { "texture": "#hair", "uv": [ 31.5, 40.5, 32.5, 43.5 ], "rotation": 90 },
								"down": { "texture": "#hair", "uv": [ 30.0, 40.5, 31.0, 43.5 ], "rotation": 270 }
							}
						},
						{
							"name": "dread5",
							"from": [ -3.5, 0.0, -1.5 ],
							"to": [ -2.5, 3.0, -0.5 ],
							"renderPass": 1,
							"uv": [ 28.0, 39.5 ],
							"rotationOrigin": [ -3.0, 3.0, -1.0 ],
							"rotationX": 10.0,
							"rotationZ": -15.0,
							"faces": {
								"north": { "texture": "#hair", "uv": [ 28.0, 40.5, 29.0, 43.5 ] },
								"east": { "texture": "#hair", "uv": [ 29.0, 40.5, 30.0, 43.5 ] },
								"south": { "texture": "#hair", "uv": [ 30.0, 40.5, 31.0, 43.5 ] },
								"west": { "texture": "#hair", "uv": [ 31.0, 40.5, 32.0, 43.5 ] },
								"up": { "texture": "#hair", "uv": [ 28.0, 39.5, 29.0, 40.5 ] },
								"down": { "texture": "#null", "uv": [ 29.0, 39.5, 30.0, 40.5 ], "enabled": false }
							}
						},
						{
							"name": "dread6",
							"from": [ -4.5, 2.0, -0.5 ],
							"to": [ -0.5, 3.0, 0.5 ],
							"autoUnwrap": false,
							"uv": [ 31.0, 28.0 ],
							"rotationOrigin": [ -2.0, 2.5, 0.0 ],
							"rotationY": 22.5,
							"rotationZ": -22.5,
							"faces": {
								"north": { "texture": "#hair", "uv": [ 28.5, 39.5, 29.5, 43.5 ], "rotation": 270 },
								"east": { "texture": "#null", "uv": [ 4.0, 1.0, 5.0, 2.0 ], "enabled": false },
								"south": { "texture": "#hair", "uv": [ 30.5, 39.5, 31.5, 43.5 ], "rotation": 90 },
								"west": { "texture": "#null", "uv": [ 9.0, 1.0, 10.0, 2.0 ], "enabled": false },
								"up": { "texture": "#hair", "uv": [ 29.5, 39.5, 30.5, 43.5 ], "rotation": 90 },
								"down": { "texture": "#hair", "uv": [ 31.0, 39.5, 32.0, 43.5 ], "rotation": 270 }
							}
						},
						{
							"name": "dread7",
							"from": [ 0.5, 2.1, 0.0 ],
							"to": [ 1.5, 6.1, 1.0 ],
							"renderPass": 1,
							"autoUnwrap": false,
							"uv": [ 29.0, 44.0 ],
							"rotationOrigin": [ 1.0, 2.1, 0.5 ],
							"rotationX": 45.0,
							"rotationY": 22.5,
							"rotationZ": 30.0,
							"faces": {
								"north": { "texture": "#hair", "uv": [ 29.0, 39.5, 30.0, 43.5 ], "rotation": 180 },
								"east": { "texture": "#hair", "uv": [ 30.0, 39.5, 31.0, 43.5 ], "rotation": 180 },
								"south": { "texture": "#hair", "uv": [ 31.0, 39.5, 32.0, 43.5 ], "rotation": 180 },
								"west": { "texture": "#hair", "uv": [ 32.0, 39.5, 33.0, 43.5 ], "rotation": 180 },
								"up": { "texture": "#null", "uv": [ 0.0, 0.0, 1.0, 1.0 ], "enabled": false },
								"down": { "texture": "#null", "uv": [ 1.0, 0.0, 2.0, 1.0 ], "enabled": false }
							}
						},
						{
							"name": "dread8",
							"from": [ -2.0, 1.6, -1.5 ],
							"to": [ 2.0, 2.6, -0.5 ],
							"renderPass": 1,
							"autoUnwrap": false,
							"uv": [ 30.5, 29.0 ],
							"rotationOrigin": [ 2.0, 2.1, -1.0 ],
							"rotationY": -45.0,
							"rotationZ": -45.0,
							"faces": {
								"north": { "texture": "#hair", "uv": [ 28.0, 39.5, 29.0, 43.5 ], "rotation": 270 },
								"east": { "texture": "#hair", "uv": [ 31.5, 34.0, 32.5, 35.0 ], "windMode": [-1,-1,-1,-1], "windData": [1,1,1,1] },
								"south": { "texture": "#hair", "uv": [ 29.5, 39.5, 30.5, 43.5 ], "rotation": 90 },
								"west": { "texture": "#null", "uv": [ 9.0, 1.0, 10.0, 2.0 ], "enabled": false },
								"up": { "texture": "#hair", "uv": [ 31.5, 39.5, 32.5, 43.5 ], "rotation": 90 },
								"down": { "texture": "#hair", "uv": [ 30.0, 39.5, 31.0, 43.5 ], "rotation": 270, "windMode": [-1,-1,-1,-1], "windData": [1,1,1,1] }
							}
						},
						{
							"name": "dread9",
							"from": [ 0.0, 2.1, -0.5 ],
							"to": [ 1.0, 6.1, 0.5 ],
							"renderPass": 1,
							"autoUnwrap": false,
							"uv": [ 29.0, 44.0 ],
							"rotationOrigin": [ 0.5, 2.1, 0.0 ],
							"rotationX": -10.0,
							"rotationZ": 22.5,
							"faces": {
								"north": { "texture": "#hair", "uv": [ 28.5, 39.5, 29.5, 43.5 ], "rotation": 180 },
								"east": { "texture": "#hair", "uv": [ 29.5, 39.5, 30.5, 43.5 ], "rotation": 180 },
								"south": { "texture": "#hair", "uv": [ 31.5, 39.5, 32.5, 43.5 ], "rotation": 180 },
								"west": { "texture": "#hair", "uv": [ 30.5, 39.5, 31.5, 43.5 ], "rotation": 180 },
								"up": { "texture": "#null", "uv": [ 0.0, 0.0, 1.0, 1.0 ], "enabled": false },
								"down": { "texture": "#null", "uv": [ 1.0, 0.0, 2.0, 1.0 ], "enabled": false }
							}
						},
						{
							"name": "hair1",
							"from": [ -4.0, 2.0, -2.5 ],
							"to": [ 1.0, 2.0, 2.5 ],
							"renderPass": 1,
							"autoUnwrap": false,
							"uv": [ 34.0, 36.5 ],
							"rotationOrigin": [ 1.0, 2.0, 0.0 ],
							"rotationZ": -22.5,
							"faces": {
								"north": { "texture": "#null", "uv": [ 0.0, 5.0, 5.0, 5.5 ], "enabled": false },
								"east": { "texture": "#null", "uv": [ 5.0, 5.0, 10.0, 5.5 ], "enabled": false },
								"south": { "texture": "#null", "uv": [ 10.0, 5.0, 15.0, 5.5 ], "enabled": false },
								"west": { "texture": "#null", "uv": [ 15.0, 5.0, 20.0, 5.5 ], "enabled": false },
								"up": { "texture": "#hair", "uv": [ 34.0, 36.5, 39.0, 41.5 ], "rotation": 90, "windMode": [-1,-1,-1,-1], "windData": [1,1,1,1] },
								"down": { "texture": "#null", "uv": [ 5.0, 0.0, 10.0, 5.0 ], "enabled": false }
							}
						},
						{
							"name": "dread10",
							"from": [ -2.5, 0.0, 1.0 ],
							"to": [ -1.5, 3.0, 2.0 ],
							"renderPass": 1,
							"uv": [ 28.0, 39.5 ],
							"rotationOrigin": [ -2.0, 3.0, 1.5 ],
							"rotationX": -22.5,
							"rotationZ": -45.0,
							"faces": {
								"north": { "texture": "#hair", "uv": [ 28.0, 40.5, 29.0, 43.5 ] },
								"east": { "texture": "#hair", "uv": [ 29.0, 40.5, 30.0, 43.5 ] },
								"south": { "texture": "#hair", "uv": [ 30.0, 40.5, 31.0, 43.5 ] },
								"west": { "texture": "#hair", "uv": [ 31.0, 40.5, 32.0, 43.5 ] },
								"up": { "texture": "#hair", "uv": [ 28.0, 39.5, 29.0, 40.5 ] },
								"down": { "texture": "#null", "uv": [ 29.0, 39.5, 30.0, 40.5 ], "enabled": false }
							}
						},
						{
							"name": "dread11",
							"from": [ 1.5, 2.1, -0.5 ],
							"to": [ 2.5, 5.1, 0.5 ],
							"renderPass": 1,
							"autoUnwrap": false,
							"uv": [ 29.0, 44.0 ],
							"rotationOrigin": [ 2.0, 2.1, 0.0 ],
							"rotationX": 30.0,
							"rotationY": 22.5,
							"rotationZ": 30.0,
							"faces": {
								"north": { "texture": "#hair", "uv": [ 29.0, 40.5, 30.0, 43.5 ], "rotation": 180 },
								"east": { "texture": "#hair", "uv": [ 30.0, 40.5, 31.0, 43.5 ], "rotation": 180 },
								"south": { "texture": "#hair", "uv": [ 31.0, 40.5, 32.0, 43.5 ], "rotation": 180 },
								"west": { "texture": "#hair", "uv": [ 32.0, 40.5, 33.0, 43.5 ], "rotation": 180 },
								"up": { "texture": "#null", "uv": [ 0.0, 0.0, 1.0, 1.0 ], "enabled": false },
								"down": { "texture": "#hair", "uv": [ 1.0, 0.0, 2.0, 1.0 ], "windMode": [-1,-1,-1,-1], "windData": [1,1,1,1] }
							}
						},
						{
							"name": "dread12",
							"from": [ 1.0, 2.1, -0.9 ],
							"to": [ 2.0, 4.1, 0.1 ],
							"renderPass": 1,
							"autoUnwrap": false,
							"uv": [ 29.0, 44.0 ],
							"rotationOrigin": [ 1.5, 2.1, -0.4 ],
							"rotationX": -10.0,
							"rotationY": -22.5,
							"faces": {
								"north": { "texture": "#hair", "uv": [ 28.5, 41.5, 29.5, 43.5 ], "rotation": 180, "windMode": [-1,-1,-1,-1], "windData": [1,1,1,1] },
								"east": { "texture": "#hair", "uv": [ 29.5, 41.5, 30.5, 43.5 ], "rotation": 180 },
								"south": { "texture": "#hair", "uv": [ 31.5, 41.5, 32.5, 43.5 ], "rotation": 180, "windMode": [-1,-1,-1,-1], "windData": [1,1,1,1] },
								"west": { "texture": "#hair", "uv": [ 30.5, 41.5, 31.5, 43.5 ], "rotation": 180, "windMode": [-1,-1,-1,-1], "windData": [1,1,1,1] },
								"up": { "texture": "#null", "uv": [ 0.0, 0.0, 1.0, 1.0 ], "enabled": false },
								"down": { "texture": "#null", "uv": [ 1.0, 0.0, 2.0, 1.0 ], "enabled": false }
							}
						},
						{
							"name": "dread13",
							"from": [ -2.5, 2.1, -2.5 ],
							"to": [ 1.5, 3.1, -1.5 ],
							"renderPass": 1,
							"autoUnwrap": false,
							"uv": [ 30.5, 29.0 ],
							"rotationOrigin": [ 0.5, 2.6, -2.0 ],
							"rotationY": -45.0,
							"rotationZ": -10.0,
							"faces": {
								"north": { "texture": "#hair", "uv": [ 28.0, 39.5, 29.0, 43.5 ], "rotation": 270 },
								"east": { "texture": "#hair", "uv": [ 31.5, 34.0, 32.5, 35.0 ], "windMode": [-1,-1,-1,-1], "windData": [1,1,1,1] },
								"south": { "texture": "#hair", "uv": [ 28.5, 39.5, 29.5, 43.5 ], "rotation": 90 },
								"west": { "texture": "#null", "uv": [ 9.0, 1.0, 10.0, 2.0 ], "enabled": false },
								"up": { "texture": "#hair", "uv": [ 31.5, 39.5, 32.5, 43.5 ], "rotation": 90 },
								"down": { "texture": "#hair", "uv": [ 30.0, 39.5, 31.0, 43.5 ], "rotation": 270 }
							}
						},
						{
							"name": "dread14",
							"from": [ -1.5, -1.0, -3.2 ],
							"to": [ -0.5, 2.5, -2.2 ],
							"renderPass": 1,
							"uv": [ 28.0, 39.0 ],
							"rotationOrigin": [ -1.0, 2.0, -2.7 ],
							"rotationX": 28.0,
							"rotationZ": -22.5,
							"faces": {
								"north": { "texture": "#hair", "uv": [ 28.0, 40.0, 29.0, 43.5 ] },
								"east": { "texture": "#hair", "uv": [ 29.0, 40.0, 30.0, 43.5 ] },
								"south": { "texture": "#hair", "uv": [ 30.0, 40.0, 31.0, 43.5 ] },
								"west": { "texture": "#hair", "uv": [ 31.0, 40.0, 32.0, 43.5 ], "windMode": [-1,-1,-1,-1], "windData": [1,1,1,1] },
								"up": { "texture": "#hair", "uv": [ 28.0, 39.0, 29.0, 40.0 ], "windMode": [-1,-1,-1,-1], "windData": [1,1,1,1] },
								"down": { "texture": "#null", "uv": [ 29.0, 39.5, 30.0, 40.5 ], "enabled": false }
							}
						},
						{
							"name": "hair2",
							"from": [ -5.0, 2.0, -2.5 ],
							"to": [ -1.0, 2.0, 2.5 ],
							"renderPass": 1,
							"autoUnwrap": false,
							"uv": [ 34.0, 36.5 ],
							"rotationOrigin": [ -1.0, 2.0, 0.0 ],
							"rotationZ": -15.0,
							"faces": {
								"north": { "texture": "#null", "uv": [ 0.0, 5.0, 4.0, 5.5 ], "enabled": false },
								"east": { "texture": "#null", "uv": [ 4.0, 5.0, 9.0, 5.5 ], "enabled": false },
								"south": { "texture": "#null", "uv": [ 9.0, 5.0, 13.0, 5.5 ], "enabled": false },
								"west": { "texture": "#null", "uv": [ 13.0, 5.0, 18.0, 5.5 ], "enabled": false },
								"up": { "texture": "#hair", "uv": [ 34.0, 37.5, 39.0, 41.5 ], "rotation": 90, "windMode": [-1,-1,-1,-1], "windData": [1,1,1,1] },
								"down": { "texture": "#null", "uv": [ 4.0, 0.0, 8.0, 5.0 ], "enabled": false }
							}
						},
						{
							"name": "hair3",
							"from": [ -6.0, 1.0, 0.0 ],
							"to": [ -2.0, 3.0, 0.0 ],
							"renderPass": 1,
							"autoUnwrap": false,
							"uv": [ 28.0, 27.5 ],
							"rotationOrigin": [ -2.0, 2.0, 0.0 ],
							"rotationY": -45.0,
							"rotationZ": -22.5,
							"faces": {
								"north": { "texture": "#hair", "uv": [ 22.0, 25.0, 24.0, 29.0 ], "rotation": 270 },
								"east": { "texture": "#null", "uv": [ 4.0, 0.5, 4.5, 2.5 ], "enabled": false },
								"south": { "texture": "#null", "uv": [ 4.5, 0.5, 8.5, 2.5 ], "enabled": false },
								"west": { "texture": "#null", "uv": [ 8.5, 0.5, 9.0, 2.5 ], "enabled": false },
								"up": { "texture": "#null", "uv": [ 0.0, 0.0, 4.0, 0.5 ], "enabled": false },
								"down": { "texture": "#null", "uv": [ 4.0, 0.0, 8.0, 0.5 ], "enabled": false }
							}
						},
						{
							"name": "hair4",
							"from": [ -6.0, 1.0, 0.0 ],
							"to": [ -2.0, 3.0, 0.0 ],
							"renderPass": 1,
							"autoUnwrap": false,
							"uv": [ 28.0, 27.5 ],
							"rotationOrigin": [ -2.0, 2.0, 0.0 ],
							"rotationY": 45.0,
							"rotationZ": -10.0,
							"faces": {
								"north": { "texture": "#hair", "uv": [ 14.5, 2.0, 16.5, 6.0 ], "rotation": 270 },
								"east": { "texture": "#null", "uv": [ 4.0, 0.5, 4.5, 2.5 ], "enabled": false },
								"south": { "texture": "#null", "uv": [ 4.5, 0.5, 8.5, 2.5 ], "enabled": false },
								"west": { "texture": "#null", "uv": [ 8.5, 0.5, 9.0, 2.5 ], "enabled": false },
								"up": { "texture": "#null", "uv": [ 0.0, 0.0, 4.0, 0.5 ], "enabled": false },
								"down": { "texture": "#null", "uv": [ 4.0, 0.0, 8.0, 0.5 ], "enabled": false }
							}
						},
						{
							"name": "fringe1",
							"from": [ -2.6, -1.0, -1.5 ],
							"to": [ -2.6, 2.0, -0.5 ],
							"renderPass": 1,
							"uv": [ 38.0, 18.5 ],
							"rotationOrigin": [ -2.6, 2.0, -1.0 ],
							"rotationX": 22.5,
							"rotationZ": -15.0,
							"faces": {
								"north": { "texture": "#null", "uv": [ 38.0, 19.5, 38.5, 22.5 ], "enabled": false },
								"east": { "texture": "#null", "uv": [ 38.5, 19.5, 39.5, 22.5 ], "enabled": false },
								"south": { "texture": "#null", "uv": [ 39.5, 19.5, 40.0, 22.5 ], "enabled": false },
								"west": { "texture": "#hair", "uv": [ 38.0, 18.5, 39.0, 21.5 ], "windMode": [-1,-1,-1,-1], "windData": [1,1,1,1] },
								"up": { "texture": "#null", "uv": [ 38.0, 18.5, 38.5, 19.5 ], "enabled": false },
								"down": { "texture": "#null", "uv": [ 38.5, 18.5, 39.0, 19.5 ], "enabled": false }
							}
						},
						{
							"name": "fringe2",
							"from": [ -2.6, -1.6, -2.3 ],
							"to": [ -2.6, 2.4, -1.3 ],
							"renderPass": 1,
							"uv": [ 24.5, 24.0 ],
							"rotationOrigin": [ -2.6, 2.4, -1.8 ],
							"rotationX": 22.5,
							"rotationY": -45.0,
							"faces": {
								"north": { "texture": "#null", "uv": [ 24.5, 25.0, 25.0, 29.0 ], "enabled": false },
								"east": { "texture": "#null", "uv": [ 25.0, 25.0, 26.0, 29.0 ], "enabled": false },
								"south": { "texture": "#null", "uv": [ 26.0, 25.0, 26.5, 29.0 ], "enabled": false },
								"west": { "texture": "#hair", "uv": [ 24.5, 24.0, 25.5, 28.0 ], "windMode": [-1,-1,-1,-1], "windData": [1,1,1,1] },
								"up": { "texture": "#null", "uv": [ 24.5, 24.0, 25.0, 25.0 ], "enabled": false },
								"down": { "texture": "#null", "uv": [ 25.0, 24.0, 25.5, 25.0 ], "enabled": false }
							}
						}
					]
				}
			]
		}
	]}